dask_traj/__init__.py
dask_traj/version.py
dask_traj/core/__init__.py
dask_traj/core/dask_traj.py
dask_traj/geometry/__init__.py
dask_traj/geometry/angle.py
dask_traj/geometry/distance.py
dask_traj/tests/__init__.py
dask_traj/tests/helpers.py
dask_traj/tests/test.pdb
dask_traj/tests/test.xtc
dask_traj/tests/test.xyz
dask_traj/tests/test_dask_traj.py
dask_traj/tests/test_geometry.py
dask_traj/tests/test_utils.py
dask_traj/utils/__init__.py
dask_traj/utils/validation.py
dask_traj-0.2.2.dist-info/LICENSE
dask_traj-0.2.2.dist-info/METADATA
dask_traj-0.2.2.dist-info/WHEEL
dask_traj-0.2.2.dist-info/top_level.txt
dask_traj-0.2.2.dist-info/RECORD
