Metadata-Version: 2.1
Name: dask-traj
Version: 0.2.2
Summary: Parallel MDTraj, using Dask
Home-page: http://github.com/sroet/dask-traj
Author: Sander Roet
Author-email: sanderroet@gmail.com
License: LGPL-2.1+
Platform: Linux
Platform: Mac OS X
Platform: Unix
Platform: Windows
Classifier: Development Status :: 4 - Beta
Classifier: Intended Audience :: Science/Research
Classifier: License :: OSI Approved :: GNU General Public License v2 or later (GPLv2+)
Classifier: Operating System :: POSIX
Classifier: Operating System :: Microsoft :: Windows
Classifier: Programming Language :: Python :: 3
Classifier: Topic :: Scientific/Engineering :: Bio-Informatics
Classifier: Topic :: Scientific/Engineering :: Chemistry
Requires-Dist: mdtraj
Requires-Dist: dask[array]
